AUTHORS.rst
CONTRIBUTING.rst
HISTORY.rst
LICENSE
MANIFEST.in
README.rst
setup.cfg
setup.py
docs/Makefile
docs/authors.rst
docs/conf.py
docs/contributing.rst
docs/history.rst
docs/index.rst
docs/installation.rst
docs/make.bat
docs/readme.rst
docs/usage.rst
tests/__init__.py
tests/test_option.py
yaopt/__init__.py
yaopt/option.py
yaopt.egg-info/PKG-INFO
yaopt.egg-info/SOURCES.txt
yaopt.egg-info/dependency_links.txt
yaopt.egg-info/not-zip-safe
yaopt.egg-info/requires.txt
yaopt.egg-info/top_level.txt